<annotation>
	<folder>results</folder>
	<filename>200.png</filename>
	<path>/home/nvidia/桌面/results/200.png</path>
	<source>
		<database>Unknown</database>
	</source>
	<size>
		<width>640</width>
		<height>512</height>
		<depth>1</depth>
	</size>
	<segmented>0</segmented>
	<object>
		<name>plane</name>
		<pose>Unspecified</pose>
		<truncated>0</truncated>
		<difficult>0</difficult>
		<bndbox>
			<xmin>178</xmin>
			<ymin>146</ymin>
			<xmax>194</xmax>
			<ymax>161</ymax>
		</bndbox>
	</object>
</annotation>
